SEM4/computer-architecture/labs/lab-quiz/branch_module.v
module branch_module (
    input [2:0] funct3,
    input ZERO,
    input BRANCH,
    output reg BEQ,
    output reg BNE
);

    always @(*)
    begin
        if(BRANCH == 1'b1)
            begin
                if (funct3 == 3'b000) // BEQ
                    begin
                        if (ZERO == 1'b1)
                            BEQ = 1'b1;
                        else
                            BEQ = 1'b0;    
                        BNE = 1'b0;
                    end
                else if (funct3 == 3'b001) // BNE
                    begin
                        if (ZERO == 1'b1)
                            BNE = 1'b0;
                        else
                            BNE = 1'b1;
                        BEQ = 1'b0;    
                    end
            end
        else
            begin
                BEQ = 1'bx;
                BNE = 1'bx;
            end
    end

endmodule

SEM4/computer-architecture/labs/lab-quiz/branch_module_tb.v
`include "branch_module.v"

`timescale 1ns/1ns

module tb();
    reg [2:0] funct3;
    reg  ZERO;
    reg  BRANCH;
    wire BEQ;
    wire BNE;

    branch_module T(
        .funct3(funct3),
        .ZERO(ZERO),
        .BRANCH(BRANCH),
        .BEQ(BEQ),
        .BNE(BNE)
    );

    initial begin
        #10
        ZERO=1'b0; BRANCH=1'b0; funct3 = 3'b000;
        #10
        ZERO=1'b0; BRANCH=1'b1; funct3 = 3'b000;
        #10
        ZERO=1'b1; BRANCH=1'b0; funct3 = 3'b000;
        #10
        ZERO=1'b1; BRANCH=1'b1; funct3 = 3'b000;
        #10
        ZERO=1'b0; BRANCH=1'b0; funct3 = 3'b001;
        #10
        ZERO=1'b0; BRANCH=1'b1; funct3 = 3'b001;
        #10
        ZERO=1'b1; BRANCH=1'b0; funct3 = 3'b001;
        #10
        ZERO=1'b1; BRANCH=1'b1; funct3 = 3'b001;
        #10
        ZERO=1'b0; BRANCH=1'b0; funct3 = 3'b011;
        #10
        ZERO=1'b0; BRANCH=1'b0; funct3 = 3'b011;
    end
    initial begin
        $dumpfile("testResults.vcd");
        $dumpvars();
    end
endmodule

computer-architecture/labs/lab-quiz/build/testResults.vcd
$date
	Fri Apr 22 09:53:31 2022
$end
$version
	Icarus Verilog
$end
$timescale
	1ns
$end
$scope module tb $end
$var wire 1 ! BNE $end
$var wire 1 " BEQ $end
$var reg 1 # BRANCH $end
$var reg 1 $ ZERO $end
$var reg 3 % funct3 [2:0] $end
$scope module T $end
$var wire 1 # BRANCH $end
$var wire 1 $ ZERO $end
$var wire 3 & funct3 [2:0] $end
$var reg 1 " BEQ $end
$var reg 1 ! BNE $end
$upscope $end
$upscope $end
$enddefinitions $end
#0
$dumpvars
bx &
bx %
x$
x#
x"
x!
$end
#10
b0 %
b0 &
0#
0$
#20
0!
0"
1#
#30
x!
x"
0#
1$
#40
0!
1"
1#
#50
x!
x"
b1 %
b1 &
0#
0$
#60
0"
1!
1#
#70
x!
x"
0#
1$
#80
0"
0!
1#
#90
x!
x"
b11 %
b11 &
0#
0$
